setup.py
which_slave/__init__.py
which_slave/which_slave.py
which_slave.egg-info/PKG-INFO
which_slave.egg-info/SOURCES.txt
which_slave.egg-info/dependency_links.txt
which_slave.egg-info/top_level.txt