Metadata-Version: 1.0
Name: which-slave
Version: 1.0
Summary: Tell me choose which slave db
Home-page: UNKNOWN
Author: Zhang Yiwei
Author-email: Karl1991223@126.com
License: public domain
Keywords: which_slave,python
Platform: any
